setup.py
django_uc.egg-info/PKG-INFO
django_uc.egg-info/SOURCES.txt
django_uc.egg-info/dependency_links.txt
django_uc.egg-info/requires.txt
django_uc.egg-info/top_level.txt
uc/__init__.py
uc/models.py