Metadata-Version: 1.1
Name: django-uc
Version: 0.0.1
Summary: Django package that helps in your UC integration
Home-page: http://github.com/FundedByMe/django-uc
Author: Rebecca Meritz
Author-email: rebecca@fundedbyme.com
License: UNKNOWN
Platform: UNKNOWN
Classifier: Framework :: Django
Classifier: Intended Audience :: Developers
Classifier: Intended Audience :: System Administrators
Classifier: Operating System :: OS Independent
Classifier: Topic :: Software Development
